MANIFEST.in
README.md
settings.ini
setup.py
phrazor/__init__.py
phrazor/exceptions.py
phrazor/generator.py
phrazor/utils.py
phrazor.egg-info/PKG-INFO
phrazor.egg-info/SOURCES.txt
phrazor.egg-info/dependency_links.txt
phrazor.egg-info/entry_points.txt
phrazor.egg-info/not-zip-safe
phrazor.egg-info/requires.txt
phrazor.egg-info/top_level.txt
phrazor/analysis/__init__.py
phrazor/analysis/analysis.py
phrazor/analysis_json/__init__.py
phrazor/analysis_json/analysis_base_json.py
phrazor/analysis_json/budget_json.py
phrazor/analysis_json/change_json.py
phrazor/analysis_json/compare_json.py
phrazor/analysis_json/descriptor_json.py
phrazor/analysis_json/forecasting_json.py
phrazor/analysis_json/target_json.py
phrazor/analysis_json/trend_json.py
phrazor/engine/__init__.py
phrazor/engine/engine.py
phrazor/engine/exceptions.py
phrazor/engine/publish.py
phrazor/messages/__init__.py
phrazor/messages/driver.py
phrazor/messages/error_messages.py
phrazor/messages/info_messages.py
phrazor/validators/__init__.py
phrazor/validators/column_validator.py
phrazor/validators/data_validator.py
phrazor/validators/filter_validator.py
phrazor/validators/request_data_validator.py