Metadata-Version: 2.1
Name: phrazor
Version: 0.0.3
Summary: Phrazor is a Python library that converts your data into textual insights.
Home-page: https://github.com/vphrase-pvt-ltd/phrazor-python/tree/master/
Author: vPhrase Analytics Solutions Pvt. Ltd.
Author-email: dev@vphrase.com
License: GNU Affero General Public License
Keywords: insights
Platform: UNKNOWN
Classifier: Development Status :: 4 - Beta
Classifier: Intended Audience :: Developers
Classifier: License :: OSI Approved :: GNU Affero General Public License v3 or later (AGPLv3+)
Classifier: Natural Language :: English
Classifier: Programming Language :: Python :: 3.6
Classifier: Programming Language :: Python :: 3.7
Classifier: Programming Language :: Python :: 3.8
Classifier: Programming Language :: Python :: 3.9
Classifier: Programming Language :: Python :: 3.10
Requires-Python: >=3.6
